{"success": true, "data": [{"account_id": 242, "name": "thehackerscrew", "date": "2022-12-09T19:48:49.012328Z", "account_url": "/teams/242"}, {"account_id": 252, "name": "FindustrieZ", "date": "2022-12-09T20:57:22.495053Z", "account_url": "/teams/252"}, {"account_id": 302, "name": "Zer0Tolerance", "date": "2022-12-09T22:33:04.539491Z", "account_url": "/teams/302"}, {"account_id": 11, "name": "CubeMastery", "date": "2022-12-09T22:36:22.316848Z", "account_url": "/teams/11"}, {"account_id": 315, "name": "b0ng0s", "date": "2022-12-10T02:07:10.896178Z", "account_url": "/teams/315"}, {"account_id": 201, "name": "squ1rrel", "date": "2022-12-10T06:11:21.903576Z", "account_url": "/teams/201"}, {"account_id": 147, "name": "polygl0ts", "date": "2022-12-10T07:50:53.885018Z", "account_url": "/teams/147"}, {"account_id": 292, "name": "dcua", "date": "2022-12-10T14:22:58.004372Z", "account_url": "/teams/292"}, {"account_id": 421, "name": "Vindicator", "date": "2022-12-10T14:37:44.384633Z", "account_url": "/teams/421"}, {"account_id": 339, "name": "idek", "date": "2022-12-10T15:05:47.824648Z", "account_url": "/teams/339"}, {"account_id": 219, "name": "fearless", "date": "2022-12-10T15:44:46.596074Z", "account_url": "/teams/219"}, {"account_id": 379, "name": "Thi5C4n7b3ReaL", "date": "2022-12-10T15:49:24.666654Z", "account_url": "/teams/379"}, {"account_id": 319, "name": "Bread is B1tter", "date": "2022-12-10T15:55:49.488258Z", "account_url": "/teams/319"}, {"account_id": 447, "name": "/mnt/ain", "date": "2022-12-10T16:41:54.562869Z", "account_url": "/teams/447"}, {"account_id": 148, "name": "saarsec", "date": "2022-12-10T16:58:06.156850Z", "account_url": "/teams/148"}, {"account_id": 161, "name": "DragonSec SI", "date": "2022-12-10T20:28:33.164171Z", "account_url": "/teams/161"}, {"account_id": 248, "name": "h4tum", "date": "2022-12-10T21:41:45.866191Z", "account_url": "/teams/248"}, {"account_id": 244, "name": "Sloppy Joe Pirates", "date": "2022-12-10T21:43:55.093001Z", "account_url": "/teams/244"}, {"account_id": 180, "name": "PPP", "date": "2022-12-10T22:31:47.242713Z", "account_url": "/teams/180"}, {"account_id": 291, "name": "0xdead", "date": "2022-12-10T22:57:21.688649Z", "account_url": "/teams/291"}, {"account_id": 241, "name": "CyberTaskForce Zero", "date": "2022-12-10T23:10:10.023604Z", "account_url": "/teams/241"}]}
